hex_modifier_tool/__init__.py
hex_modifier_tool-0.1.0.dist-info/licenses/LICENSE
hex_modifier_tool-0.1.0.dist-info/METADATA
hex_modifier_tool-0.1.0.dist-info/WHEEL
hex_modifier_tool-0.1.0.dist-info/entry_points.txt
hex_modifier_tool-0.1.0.dist-info/top_level.txt
hex_modifier_tool-0.1.0.dist-info/RECORD
