Metadata-Version: 2.4
Name: hex_modifier_tool
Version: 0.1.0
Summary: Small to to modify hex files
Author-email: Fabian Pflug <fabian.pflug@gumulka.eu>
License-Expression: MIT
Project-URL: Homepage, https://github.com/gumulka/hex_modifier_tool
Project-URL: Issues, https://github.com/gumulka/hex_modifier_tool/issues
Classifier: Programming Language :: Python :: 3
Classifier: Operating System :: OS Independent
Requires-Python: >=3.9
License-File: LICENSE
Requires-Dist: intelhex>=2.3.0
Dynamic: license-file
